lujia_utils/__init__.py
lujia_utils/nonblock_server/__init__.py
lujia_utils/nonblock_server/nonblock_server.py
lujia_utils/vis_image/__init__.py
lujia_utils/vis_image/vis_image.py
lujia_utils-1.1.dist-info/LICENSE
lujia_utils-1.1.dist-info/METADATA
lujia_utils-1.1.dist-info/WHEEL
lujia_utils-1.1.dist-info/top_level.txt
lujia_utils-1.1.dist-info/RECORD
