Metadata-Version: 2.1
Name: lujia-utils
Version: 1.1
Summary: util packages for zjulujia
Home-page: https://github.com/zjulujia/ssd.pytorch
Author: zjulujia
Author-email: zjulujia@gmail.com
License: UNKNOWN
Platform: UNKNOWN
Classifier: Programming Language :: Python :: 3
Classifier: License :: OSI Approved :: MIT License
Classifier: Operating System :: OS Independent
License-File: LICENSE
Requires-Dist: matplotlib (>=3.5.1)
Requires-Dist: mpld3 (>=0.5.7)
Requires-Dist: numpy (>=1.20.0)
